inspect_policy_sandbox/__init__.py
inspect_policy_sandbox/policy.py
inspect_policy_sandbox/sandbox.py
inspect_policy_sandbox-0.1.3.dist-info/licenses/LICENSE
inspect_policy_sandbox-0.1.3.dist-info/METADATA
inspect_policy_sandbox-0.1.3.dist-info/WHEEL
inspect_policy_sandbox-0.1.3.dist-info/entry_points.txt
inspect_policy_sandbox-0.1.3.dist-info/top_level.txt
inspect_policy_sandbox-0.1.3.dist-info/RECORD
