Metadata-Version: 2.4
Name: inspect-policy-sandbox
Version: 0.1.3
Summary: Inspect AI extension for policy-enforced sandbox environments
Author-email: Arnab Mitra <papan.mitra.2121@gmail.com>
Project-URL: Repository, https://github.com/Dedulus/inspect-policy-sandbox
Project-URL: Issues, https://github.com/Dedulus/inspect-policy-sandbox/issues
Classifier: Programming Language :: Python :: 3
Classifier: License :: OSI Approved :: MIT License
Classifier: Operating System :: OS Independent
Requires-Python: >=3.11
License-File: LICENSE
Requires-Dist: inspect-ai
Provides-Extra: dev
Requires-Dist: pytest; extra == "dev"
Requires-Dist: pytest-asyncio; extra == "dev"
Dynamic: license-file
